jutl/__init__.py
jutl/averages/__init__.py
jutl/benchmarking/__init__.py
jutl/benchmarking/latency.py
jutl/calculators/__init__.py
jutl/converters/__init__.py
jutl/cryptography/__init__.py
jutl/cryptography/caesarcipher.py
jutl/cryptography/rot13cipher.py
jutl/cryptography/substitutioncipher.py
jutl/datastructures/__init__.py
jutl/datastructures/queue.py
jutl/datastructures/stack.py
jutl/exceptions/__init__.py
jutl/exceptions/emptypipeline.py
jutl/exceptions/emptyqueue.py
jutl/exceptions/emptystack.py
jutl/exceptions/fullqueue.py
jutl/exceptions/fullstack.py
jutl/exceptions/invalidformatting.py
jutl/exceptions/jutlexception.py
jutl/exceptions/missinginput.py
jutl/formatting/__init__.py
jutl/formatting/color.py
jutl/formatting/text.py
jutl/formatting/utils.py
jutl/language/__init__.py
jutl/logic/__init__.py
jutl/pipelining/__init__.py
jutl/pipelining/datapipeline.py
jutl/pipelining/instructionpipeline.py
jutl/sorters/__init__.py
jutl/timers/__init__.py
jutl/timers/reporter.py
jutl/timers/stopwatch.py
jutl/timers/timer.py
jutl/utilities/__init__.py
jutl/utilities/helloworld.py
jutl-0.5.3.dist-info/LICENSE.md
jutl-0.5.3.dist-info/METADATA
jutl-0.5.3.dist-info/WHEEL
jutl-0.5.3.dist-info/top_level.txt
jutl-0.5.3.dist-info/RECORD
