Metadata-Version: 2.1
Name: jutl
Version: 0.5.3
Summary: A Python package of useful tools and utilities.
Home-page: https://pypi.org/project/jutl/
Download-URL: https://github.com/JordanWelsman/jutils/tags
Author: Jordan Welsman
Author-email: jordan.welsman@outlook.com
License: MIT
Keywords: python,averages,calculators,converters,cryptography,formatting,language,logic,pipelining,sorters,timers,utilities
Classifier: Development Status :: 4 - Beta
Classifier: Intended Audience :: Developers
Classifier: Intended Audience :: Education
Classifier: License :: OSI Approved :: MIT License
Classifier: Topic :: Education
Classifier: Topic :: Scientific/Engineering
Classifier: Topic :: Scientific/Engineering :: Mathematics
Classifier: Topic :: Security
Classifier: Topic :: Security :: Cryptography
Classifier: Topic :: Software Development
Classifier: Topic :: Software Development :: Libraries
Classifier: Topic :: Software Development :: Libraries :: Python Modules
Classifier: Topic :: Utilities
Classifier: Programming Language :: Python
Classifier: Programming Language :: Python :: 3
Classifier: Programming Language :: Python :: 3.10
Classifier: Programming Language :: Python :: 3.11
Requires-Python: >=3.10
License-File: LICENSE.md
